{
  "generated_at": "2026-02-15T13:50:18.719516+00:00",
  "source": "github_actions",
  "failed_count": 1,
  "failed_sites": [
    {
      "provider": "hotaru",
      "account_name": "主账号_hotaru",
      "api_user": "",
      "platform": "NewAPI (hotaru)",
      "site_url": "https://api.hotaruapi.top",
      "login_url": "https://api.hotaruapi.top/login",
      "oauth_login_url": "https://api.hotaruapi.top/auth/login?returnTo=%2F",
      "reason": "LinuxDO 登录失败",
      "failure_kind": "",
      "runtime_cookie_keys": [],
      "last_url": "",
      "needs_manual_auth": true,
      "oauth_cookie_blocked": true
    }
  ]
}